terminal_video_player_py.py
to_ascii.py
vid_info.py
terminal_video_player_py-1.0.2.dist-info/LICENSE
terminal_video_player_py-1.0.2.dist-info/METADATA
terminal_video_player_py-1.0.2.dist-info/WHEEL
terminal_video_player_py-1.0.2.dist-info/entry_points.txt
terminal_video_player_py-1.0.2.dist-info/top_level.txt
terminal_video_player_py-1.0.2.dist-info/RECORD
