Metadata-Version: 2.2
Name: terminal_video_player_py
Version: 1.0.2
Summary: A cli to play videos in the terminal.
Home-page: 
Author: 
Author-email: 
Requires-Python: >=3.9
License-File: LICENSE
Requires-Dist: fpstimer
Requires-Dist: playsound==1.2.2
Requires-Dist: cursor
Requires-Dist: pydub
Requires-Dist: opencv-python
Requires-Dist: Pillow
Dynamic: description
Dynamic: description-content-type
Dynamic: requires-dist
Dynamic: requires-python
Dynamic: summary
